zuu/app/clipchamp.py
zuu/app/obsidian.py
zuu/app/scoop.py
zuu/app/steam.py
zuu/pkg/flask.py
zuu/std/dict.py
zuu/std/hmac.py
zuu/std/json.py
zuu/std/string.py
zuu/std/time.py
zuu/u/class_prop.py
zuu/u/dart.py
zuu/u/dart_slang_migration.py
zuu/u/date_folder_struct.py
zuu/u/dict_patterns.py
zuu/u/diffdict.py
zuu/u/geo_lookup.py
zuu/u/image_base64_conversion.py
zuu/u/match_string.py
zuu/u/process_watchdog.py
zuu/u/syncdict.py
zuu/u/task_scheduler.py
zuu-25.9.10001.dist-info/METADATA
zuu-25.9.10001.dist-info/WHEEL
zuu-25.9.10001.dist-info/licenses/LICENSE
zuu-25.9.10001.dist-info/RECORD
