Metadata-Version: 2.4
Name: zuu
Version: 25.9.10001
Summary: Zack's Useful Utilities - A collection of Python utilities for various tasks.
Author-email: ZackaryW <gitzackw@gmail.com>
License-File: LICENSE
Requires-Python: >=3.8
